json_placeholder/__init__.py
json_placeholder_client-1.1.1.dist-info/METADATA
json_placeholder_client-1.1.1.dist-info/RECORD
json_placeholder_client-1.1.1.dist-info/WHEEL
json_placeholder_client-1.1.1.dist-info/top_level.txt
