Metadata-Version: 2.1
Name: json-placeholder-client
Version: 1.1.1
Summary: Client for JSON-Placeholder
Home-page: UNKNOWN
Author: UNKNOWN
Author-email: UNKNOWN
License: UNKNOWN
Platform: UNKNOWN
Requires-Dist: requests
